telegram_sender/__init__.py
telegram_sender/core.py
telegram_sender-1.6.1.dist-info/METADATA
telegram_sender-1.6.1.dist-info/WHEEL
telegram_sender-1.6.1.dist-info/top_level.txt
telegram_sender-1.6.1.dist-info/RECORD
