Metadata-Version: 2.4
Name: telegram_sender
Version: 1.6.1
Summary: Asynchronous Python tool for efficiently sending messages and photos to multiple Telegram users with optional MongoDB logging.
Author-email: Alexander Smirnov <Alex@TheSmirnov.com>
Project-URL: Homepage, https://github.com/smalyu/telegram_sender
Project-URL: Bug Tracker, https://github.com/smalyu/telegram_sender/issues
Project-URL: Source, https://github.com/smalyu/telegram_sender
Keywords: telegram,bot,async,message,sender
Classifier: Typing :: Typed
Classifier: Intended Audience :: Developers
Classifier: Framework :: AsyncIO
Classifier: Programming Language :: Python :: 3.10
Classifier: Programming Language :: Python :: 3.11
Classifier: Programming Language :: Python :: 3.12
Classifier: Programming Language :: Python :: 3.13
Classifier: Programming Language :: Python :: 3.14
Classifier: Operating System :: OS Independent
Classifier: Operating System :: POSIX
Classifier: Operating System :: MacOS
Classifier: Operating System :: POSIX :: Linux
Classifier: Operating System :: Microsoft :: Windows
Classifier: Topic :: Software Development :: Libraries :: Python Modules
Requires-Python: >=3.10
Requires-Dist: aiohttp<4,>=3
Requires-Dist: pymongo<5,>=4.6
Requires-Dist: pydantic<3,>=2
